{"ICAO": "LEGR", "IATA": "GRX", "name": "Federico Garc\u00eda Lorca Granada-Ja\u00e9n", "regionName": "Spain", "elevation": 1860.0000028272, "lat": 37.1887, "lon": -3.77735, "magneticVariation": -0.0031454526040721373, "timezone": {"name": "Europe/Madrid", "offset": 3600}, "times": {"sunrise": "2023-12-04T07:13:58.945Z", "sunset": "2023-12-04T16:59:15.939Z", "dawn": "2023-12-04T06:45:14.444Z", "dusk": "2023-12-04T17:28:00.439Z"}, "runwayCount": 1, "runways": [{"ident": "09", "width": 147.998687889, "length": 9497.145683727, "bearing": 89.46, "surface": "ASPHALT", "markings": ["PREC-APP"], "lighting": ["CENTERLINE", "EDGE", "THRESHOLD", "ALSF-I", "REIL-OMNI"], "thresholdOffset": 0, "overrunLength": 193.5695541, "ends": [{"ident": "09", "lat": 37.1886, "lon": -3.79369}, {"ident": "27", "lat": 37.1889, "lon": -3.76102}], "navaids": [{"ident": "GRD", "type": "GS", "lat": 37.1886, "lon": -3.79372, "airport": "LEGR", "runway": "09", "frequency": 109300000, "slope": 3.00089, "bearing": 89.48, "name": null, "elevation": 1856.0006589891, "range": 9.999999991560001}, {"ident": "OM", "type": "OM", "lat": 37.1879, "lon": -3.87835, "airport": "LEGR", "runway": "09", "frequency": null, "slope": null, "bearing": 89.47, "name": null, "elevation": 1858.9993466577002, "range": 0}, {"ident": "GRD", "type": "LOC-ILS", "lat": 37.1886, "lon": -3.79372, "airport": "LEGR", "runway": "09", "frequency": 109300000, "slope": null, "bearing": 89.48, "name": "ILS-cat-I", "elevation": 1856.0006589891, "range": 17.999999984808}, {"ident": "MM", "type": "MM", "lat": 37.1885, "lon": -3.80588, "airport": "LEGR", "runway": "09", "frequency": null, "slope": null, "bearing": 89.47, "name": null, "elevation": 1858.9993466577002, "range": 0}]}, {"ident": "27", "width": 147.998687889, "length": 9497.145683727, "bearing": 269.48, "surface": "ASPHALT", "markings": ["PREC-APP"], "lighting": ["CENTERLINE", "EDGE", "THRESHOLD", "SALS", "REIL-OMNI"], "thresholdOffset": 0, "overrunLength": 196.850394, "ends": [{"ident": "27", "lat": 37.1889, "lon": -3.76102}, {"ident": "09", "lat": 37.1886, "lon": -3.79369}], "navaids": []}], "frequencies": [{"type": "GND", "frequency": 121700000, "name": "Granada Ground"}, {"type": "APP", "frequency": 118850000, "name": "Granada Approach"}, {"type": "TWR", "frequency": 118850000, "name": "Granada Tower"}], "weather": {"METAR": "LEGR 041930Z VRB01KT 3000 -RA SCT010 BKN060 08/08 Q1020", "TAF": "TAF LEGR 041700Z 0418/0518 VRB02KT 9999 FEW040 TX10/0515Z TN04/0506Z PROB30 TEMPO 0418/0420 4000 RA BKN012 PROB40 TEMPO 0422/0510 2000 BR BKN008 PROB30 TEMPO 0500/0508 0200 FG VV001"}}